{
    "id2rgb": {
        "0": [
            130,
            219,
            128
        ],
        "1": [
            42,
            174,
            203
        ],
        "2": [
            224,
            172,
            177
        ],
        "3": [
            145,
            183,
            160
        ],
        "4": [
            137,
            241,
            224
        ],
        "5": [
            132,
            224,
            232
        ],
        "6": [
            105,
            64,
            153
        ],
        "7": [
            227,
            217,
            179
        ],
        "8": [
            91,
            214,
            208
        ],
        "9": [
            219,
            213,
            192
        ],
        "10": [
            229,
            90,
            95
        ],
        "11": [
            248,
            71,
            170
        ],
        "12": [
            199,
            173,
            249
        ],
        "13": [
            85,
            228,
            205
        ],
        "14": [
            208,
            160,
            121
        ],
        "15": [
            180,
            238,
            141
        ],
        "16": [
            53,
            246,
            59
        ],
        "17": [
            50,
            96,
            227
        ],
        "18": [
            93,
            140,
            183
        ],
        "19": [
            138,
            126,
            0
        ],
        "20": [
            143,
            125,
            199
        ],
        "21": [
            197,
            201,
            242
        ],
        "22": [
            214,
            186,
            202
        ],
        "23": [
            46,
            109,
            226
        ],
        "24": [
            208,
            182,
            232
        ],
        "25": [
            133,
            124,
            235
        ],
        "26": [
            233,
            152,
            235
        ],
        "27": [
            223,
            192,
            223
        ],
        "28": [
            232,
            145,
            127
        ],
        "29": [
            206,
            254,
            170
        ],
        "30": [
            184,
            81,
            185
        ],
        "31": [
            142,
            190,
            77
        ],
        "32": [
            190,
            247,
            227
        ],
        "33": [
            216,
            254,
            163
        ],
        "34": [
            158,
            253,
            220
        ],
        "35": [
            249,
            209,
            160
        ],
        "36": [
            13,
            95,
            229
        ],
        "37": [
            243,
            61,
            255
        ],
        "38": [
            250,
            227,
            104
        ],
        "39": [
            121,
            209,
            239
        ],
        "40": [
            236,
            255,
            157
        ],
        "41": [
            189,
            28,
            203
        ],
        "42": [
            173,
            98,
            162
        ],
        "43": [
            160,
            243,
            233
        ],
        "44": [
            120,
            148,
            186
        ],
        "45": [
            147,
            128,
            167
        ],
        "46": [
            247,
            189,
            186
        ],
        "47": [
            175,
            203,
            240
        ],
        "48": [
            102,
            203,
            156
        ],
        "49": [
            98,
            142,
            215
        ],
        "50": [
            186,
            188,
            106
        ],
        "51": [
            101,
            77,
            131
        ],
        "52": [
            182,
            130,
            192
        ],
        "53": [
            179,
            185,
            238
        ],
        "54": [
            229,
            0,
            182
        ],
        "55": [
            162,
            190,
            241
        ],
        "56": [
            71,
            160,
            251
        ],
        "57": [
            249,
            205,
            124
        ],
        "58": [
            205,
            166,
            230
        ],
        "59": [
            220,
            199,
            221
        ],
        "60": [
            115,
            245,
            165
        ],
        "61": [
            191,
            250,
            191
        ],
        "62": [
            95,
            224,
            219
        ],
        "63": [
            225,
            240,
            13
        ],
        "64": [
            171,
            249,
            167
        ],
        "65": [
            238,
            212,
            161
        ],
        "66": [
            237,
            127,
            138
        ],
        "67": [
            189,
            139,
            200
        ],
        "68": [
            231,
            170,
            231
        ],
        "69": [
            148,
            150,
            237
        ],
        "70": [
            253,
            79,
            245
        ],
        "71": [
            86,
            232,
            175
        ],
        "72": [
            73,
            226,
            210
        ],
        "73": [
            246,
            85,
            206
        ],
        "74": [
            159,
            178,
            206
        ],
        "75": [
            175,
            83,
            251
        ],
        "76": [
            104,
            73,
            140
        ],
        "77": [
            163,
            236,
            219
        ],
        "78": [
            113,
            218,
            213
        ],
        "79": [
            200,
            222,
            125
        ],
        "80": [
            176,
            229,
            252
        ],
        "81": [
            215,
            135,
            88
        ],
        "82": [
            248,
            88,
            168
        ],
        "83": [
            198,
            227,
            224
        ],
        "84": [
            140,
            105,
            254
        ],
        "85": [
            201,
            149,
            249
        ],
        "86": [
            196,
            101,
            247
        ],
        "87": [
            156,
            244,
            182
        ],
        "88": [
            174,
            102,
            93
        ],
        "89": [
            255,
            167,
            150
        ],
        "90": [
            96,
            208,
            178
        ],
        "91": [
            250,
            122,
            148
        ],
        "92": [
            254,
            242,
            139
        ],
        "93": [
            148,
            171,
            118
        ],
        "94": [
            237,
            245,
            50
        ],
        "95": [
            170,
            249,
            69
        ],
        "96": [
            144,
            66,
            163
        ],
        "97": [
            226,
            255,
            225
        ],
        "98": [
            210,
            112,
            254
        ],
        "99": [
            182,
            216,
            86
        ],
        "100": [
            244,
            250,
            221
        ],
        "101": [
            166,
            245,
            213
        ],
        "102": [
            199,
            236,
            250
        ],
        "103": [
            81,
            194,
            145
        ],
        "104": [
            169,
            178,
            208
        ],
        "105": [
            64,
            162,
            236
        ],
        "106": [
            200,
            196,
            211
        ],
        "107": [
            219,
            175,
            169
        ],
        "108": [
            186,
            181,
            126
        ],
        "109": [
            99,
            217,
            28
        ],
        "110": [
            167,
            136,
            110
        ],
        "111": [
            203,
            195,
            222
        ],
        "112": [
            168,
            233,
            159
        ],
        "113": [
            242,
            199,
            144
        ],
        "114": [
            222,
            108,
            246
        ],
        "115": [
            236,
            34,
            236
        ],
        "116": [
            139,
            235,
            75
        ],
        "117": [
            192,
            121,
            178
        ],
        "118": [
            136,
            113,
            119
        ],
        "119": [
            187,
            170,
            238
        ],
        "120": [
            194,
            248,
            130
        ],
        "121": [
            235,
            191,
            242
        ],
        "122": [
            230,
            144,
            199
        ],
        "123": [
            220,
            215,
            237
        ],
        "124": [
            178,
            110,
            253
        ],
        "125": [
            141,
            186,
            233
        ],
        "126": [
            252,
            222,
            241
        ],
        "127": [
            118,
            200,
            142
        ],
        "128": [
            79,
            156,
            248
        ],
        "129": [
            241,
            180,
            174
        ],
        "130": [
            90,
            236,
            129
        ],
        "131": [
            114,
            200,
            218
        ],
        "132": [
            214,
            223,
            120
        ],
        "133": [
            119,
            155,
            239
        ],
        "134": [
            238,
            211,
            205
        ],
        "135": [
            223,
            237,
            135
        ],
        "136": [
            184,
            219,
            228
        ],
        "137": [
            213,
            198,
            230
        ],
        "138": [
            66,
            22,
            190
        ],
        "139": [
            178,
            223,
            188
        ],
        "140": [
            177,
            242,
            209
        ],
        "141": [
            217,
            206,
            117
        ],
        "142": [
            197,
            157,
            137
        ],
        "143": [
            209,
            226,
            181
        ],
        "144": [
            151,
            99,
            66
        ],
        "145": [
            213,
            117,
            229
        ],
        "146": [
            22,
            153,
            147
        ],
        "147": [
            235,
            106,
            132
        ],
        "148": [
            241,
            104,
            146
        ],
        "149": [
            109,
            241,
            164
        ],
        "150": [
            239,
            213,
            155
        ],
        "151": [
            215,
            131,
            207
        ],
        "152": [
            247,
            161,
            73
        ],
        "153": [
            155,
            164,
            98
        ],
        "154": [
            252,
            230,
            102
        ],
        "155": [
            234,
            146,
            136
        ],
        "156": [
            173,
            246,
            189
        ],
        "157": [
            110,
            179,
            244
        ],
        "158": [
            164,
            147,
            105
        ],
        "159": [
            204,
            243,
            247
        ],
        "160": [
            127,
            235,
            134
        ],
        "161": [
            210,
            163,
            64
        ],
        "162": [
            0,
            215,
            196
        ],
        "163": [
            255,
            211,
            196
        ],
        "164": [
            161,
            163,
            180
        ],
        "165": [
            222,
            56,
            220
        ],
        "166": [
            134,
            93,
            210
        ],
        "167": [
            226,
            247,
            198
        ],
        "168": [
            112,
            206,
            61
        ],
        "169": [
            245,
            175,
            148
        ],
        "170": [
            183,
            53,
            202
        ],
        "171": [
            251,
            13,
            197
        ],
        "172": [
            228,
            193,
            244
        ],
        "173": [
            245,
            133,
            38
        ],
        "174": [
            152,
            253,
            245
        ],
        "175": [
            129,
            177,
            197
        ],
        "176": [
            205,
            143,
            222
        ],
        "177": [
            135,
            221,
            22
        ],
        "178": [
            242,
            240,
            194
        ],
        "179": [
            240,
            220,
            184
        ],
        "180": [
            28,
            251,
            211
        ],
        "181": [
            196,
            42,
            216
        ],
        "182": [
            234,
            132,
            248
        ],
        "183": [
            56,
            115,
            252
        ],
        "184": [
            125,
            154,
            155
        ],
        "185": [
            211,
            252,
            240
        ],
        "186": [
            202,
            69,
            158
        ],
        "187": [
            180,
            218,
            176
        ],
        "188": [
            83,
            155,
            228
        ],
        "189": [
            185,
            233,
            246
        ],
        "190": [
            117,
            148,
            53
        ],
        "191": [
            122,
            86,
            217
        ],
        "192": [
            253,
            207,
            204
        ],
        "193": [
            233,
            176,
            201
        ],
        "194": [
            69,
            244,
            212
        ],
        "195": [
            230,
            252,
            234
        ],
        "196": [
            203,
            232,
            152
        ],
        "197": [
            236,
            239,
            218
        ],
        "198": [
            108,
            50,
            91
        ],
        "199": [
            124,
            180,
            250
        ],
        "200": [
            224,
            141,
            173
        ],
        "201": [
            195,
            229,
            85
        ],
        "202": [
            212,
            159,
            214
        ],
        "203": [
            131,
            230,
            193
        ],
        "204": [
            157,
            118,
            42
        ],
        "205": [
            217,
            187,
            172
        ],
        "206": [
            228,
            252,
            215
        ],
        "207": [
            194,
            214,
            214
        ],
        "208": [
            153,
            197,
            243
        ],
        "209": [
            221,
            231,
            46
        ],
        "210": [
            252,
            134,
            83
        ],
        "211": [
            150,
            168,
            245
        ],
        "212": [
            172,
            138,
            187
        ],
        "213": [
            206,
            158,
            101
        ],
        "214": [
            254,
            205,
            195
        ],
        "215": [
            193,
            46,
            113
        ],
        "216": [
            218,
            167,
            79
        ],
        "217": [
            240,
            202,
            151
        ],
        "218": [
            221,
            220,
            190
        ],
        "219": [
            106,
            184,
            175
        ],
        "220": [
            165,
            194,
            133
        ],
        "221": [
            163,
            165,
            234
        ],
        "222": [
            75,
            120,
            184
        ],
        "223": [
            209,
            228,
            194
        ],
        "224": [
            38,
            75,
            223
        ],
        "225": [
            202,
            238,
            109
        ],
        "226": [
            192,
            197,
            231
        ],
        "227": [
            146,
            151,
            252
        ],
        "228": [
            218,
            137,
            149
        ],
        "229": [
            149,
            251,
            112
        ],
        "230": [
            34,
            204,
            71
        ],
        "231": [
            77,
            192,
            180
        ],
        "232": [
            246,
            184,
            34
        ],
        "233": [
            244,
            173,
            217
        ],
        "234": [
            61,
            182,
            81
        ],
        "235": [
            167,
            38,
            171
        ],
        "236": [
            126,
            189,
            122
        ],
        "237": [
            88,
            225,
            96
        ],
        "238": [
            211,
            210,
            90
        ],
        "239": [
            154,
            208,
            56
        ],
        "240": [
            190,
            114,
            173
        ],
        "241": [
            170,
            237,
            115
        ],
        "242": [
            239,
            169,
            255
        ],
        "243": [
            227,
            202,
            99
        ],
        "244": [
            160,
            239,
            236
        ],
        "245": [
            243,
            234,
            143
        ],
        "246": [
            155,
            221,
            166
        ],
        "247": [
            245,
            248,
            154
        ],
        "248": [
            188,
            210,
            253
        ],
        "249": [
            251,
            59,
            226
        ],
        "250": [
            207,
            91,
            108
        ],
        "251": [
            231,
            196,
            243
        ],
        "252": [
            128,
            129,
            189
        ],
        "253": [
            59,
            234,
            200
        ],
        "254": [
            181,
            231,
            209
        ],
        "255": [
            232,
            119,
            114
        ]
    },
    "rgb2id": {
        "130": {
            "219": {
                "128": 0
            }
        },
        "42": {
            "174": {
                "203": 1
            }
        },
        "224": {
            "172": {
                "177": 2
            },
            "141": {
                "173": 200
            }
        },
        "145": {
            "183": {
                "160": 3
            }
        },
        "137": {
            "241": {
                "224": 4
            }
        },
        "132": {
            "224": {
                "232": 5
            }
        },
        "105": {
            "64": {
                "153": 6
            }
        },
        "227": {
            "217": {
                "179": 7
            },
            "202": {
                "99": 243
            }
        },
        "91": {
            "214": {
                "208": 8
            }
        },
        "219": {
            "213": {
                "192": 9
            },
            "175": {
                "169": 107
            }
        },
        "229": {
            "90": {
                "95": 10
            },
            "0": {
                "182": 54
            }
        },
        "248": {
            "71": {
                "170": 11
            },
            "88": {
                "168": 82
            }
        },
        "199": {
            "173": {
                "249": 12
            },
            "236": {
                "250": 102
            }
        },
        "85": {
            "228": {
                "205": 13
            }
        },
        "208": {
            "160": {
                "121": 14
            },
            "182": {
                "232": 24
            }
        },
        "180": {
            "238": {
                "141": 15
            },
            "218": {
                "176": 187
            }
        },
        "53": {
            "246": {
                "59": 16
            }
        },
        "50": {
            "96": {
                "227": 17
            }
        },
        "93": {
            "140": {
                "183": 18
            }
        },
        "138": {
            "126": {
                "0": 19
            }
        },
        "143": {
            "125": {
                "199": 20
            }
        },
        "197": {
            "201": {
                "242": 21
            },
            "157": {
                "137": 142
            }
        },
        "214": {
            "186": {
                "202": 22
            },
            "223": {
                "120": 132
            }
        },
        "46": {
            "109": {
                "226": 23
            }
        },
        "133": {
            "124": {
                "235": 25
            }
        },
        "233": {
            "152": {
                "235": 26
            },
            "176": {
                "201": 193
            }
        },
        "223": {
            "192": {
                "223": 27
            },
            "237": {
                "135": 135
            }
        },
        "232": {
            "145": {
                "127": 28
            },
            "119": {
                "114": 255
            }
        },
        "206": {
            "254": {
                "170": 29
            },
            "158": {
                "101": 213
            }
        },
        "184": {
            "81": {
                "185": 30
            },
            "219": {
                "228": 136
            }
        },
        "142": {
            "190": {
                "77": 31
            }
        },
        "190": {
            "247": {
                "227": 32
            },
            "114": {
                "173": 240
            }
        },
        "216": {
            "254": {
                "163": 33
            }
        },
        "158": {
            "253": {
                "220": 34
            }
        },
        "249": {
            "209": {
                "160": 35
            },
            "205": {
                "124": 57
            }
        },
        "13": {
            "95": {
                "229": 36
            }
        },
        "243": {
            "61": {
                "255": 37
            },
            "234": {
                "143": 245
            }
        },
        "250": {
            "227": {
                "104": 38
            },
            "122": {
                "148": 91
            }
        },
        "121": {
            "209": {
                "239": 39
            }
        },
        "236": {
            "255": {
                "157": 40
            },
            "34": {
                "236": 115
            },
            "239": {
                "218": 197
            }
        },
        "189": {
            "28": {
                "203": 41
            },
            "139": {
                "200": 67
            }
        },
        "173": {
            "98": {
                "162": 42
            },
            "246": {
                "189": 156
            }
        },
        "160": {
            "243": {
                "233": 43
            },
            "239": {
                "236": 244
            }
        },
        "120": {
            "148": {
                "186": 44
            }
        },
        "147": {
            "128": {
                "167": 45
            }
        },
        "247": {
            "189": {
                "186": 46
            },
            "161": {
                "73": 152
            }
        },
        "175": {
            "203": {
                "240": 47
            },
            "83": {
                "251": 75
            }
        },
        "102": {
            "203": {
                "156": 48
            }
        },
        "98": {
            "142": {
                "215": 49
            }
        },
        "186": {
            "188": {
                "106": 50
            },
            "181": {
                "126": 108
            }
        },
        "101": {
            "77": {
                "131": 51
            }
        },
        "182": {
            "130": {
                "192": 52
            },
            "216": {
                "86": 99
            }
        },
        "179": {
            "185": {
                "238": 53
            }
        },
        "162": {
            "190": {
                "241": 55
            }
        },
        "71": {
            "160": {
                "251": 56
            }
        },
        "205": {
            "166": {
                "230": 58
            },
            "143": {
                "222": 176
            }
        },
        "220": {
            "199": {
                "221": 59
            },
            "215": {
                "237": 123
            }
        },
        "115": {
            "245": {
                "165": 60
            }
        },
        "191": {
            "250": {
                "191": 61
            }
        },
        "95": {
            "224": {
                "219": 62
            }
        },
        "225": {
            "240": {
                "13": 63
            }
        },
        "171": {
            "249": {
                "167": 64
            }
        },
        "238": {
            "212": {
                "161": 65
            },
            "211": {
                "205": 134
            }
        },
        "237": {
            "127": {
                "138": 66
            },
            "245": {
                "50": 94
            }
        },
        "231": {
            "170": {
                "231": 68
            },
            "196": {
                "243": 251
            }
        },
        "148": {
            "150": {
                "237": 69
            },
            "171": {
                "118": 93
            }
        },
        "253": {
            "79": {
                "245": 70
            },
            "207": {
                "204": 192
            }
        },
        "86": {
            "232": {
                "175": 71
            }
        },
        "73": {
            "226": {
                "210": 72
            }
        },
        "246": {
            "85": {
                "206": 73
            },
            "184": {
                "34": 232
            }
        },
        "159": {
            "178": {
                "206": 74
            }
        },
        "104": {
            "73": {
                "140": 76
            }
        },
        "163": {
            "236": {
                "219": 77
            },
            "165": {
                "234": 221
            }
        },
        "113": {
            "218": {
                "213": 78
            }
        },
        "200": {
            "222": {
                "125": 79
            },
            "196": {
                "211": 106
            }
        },
        "176": {
            "229": {
                "252": 80
            }
        },
        "215": {
            "135": {
                "88": 81
            },
            "131": {
                "207": 151
            }
        },
        "198": {
            "227": {
                "224": 83
            }
        },
        "140": {
            "105": {
                "254": 84
            }
        },
        "201": {
            "149": {
                "249": 85
            }
        },
        "196": {
            "101": {
                "247": 86
            },
            "42": {
                "216": 181
            }
        },
        "156": {
            "244": {
                "182": 87
            }
        },
        "174": {
            "102": {
                "93": 88
            }
        },
        "255": {
            "167": {
                "150": 89
            },
            "211": {
                "196": 163
            }
        },
        "96": {
            "208": {
                "178": 90
            }
        },
        "254": {
            "242": {
                "139": 92
            },
            "205": {
                "195": 214
            }
        },
        "170": {
            "249": {
                "69": 95
            },
            "237": {
                "115": 241
            }
        },
        "144": {
            "66": {
                "163": 96
            }
        },
        "226": {
            "255": {
                "225": 97
            },
            "247": {
                "198": 167
            }
        },
        "210": {
            "112": {
                "254": 98
            },
            "163": {
                "64": 161
            }
        },
        "244": {
            "250": {
                "221": 100
            },
            "173": {
                "217": 233
            }
        },
        "166": {
            "245": {
                "213": 101
            }
        },
        "81": {
            "194": {
                "145": 103
            }
        },
        "169": {
            "178": {
                "208": 104
            }
        },
        "64": {
            "162": {
                "236": 105
            }
        },
        "99": {
            "217": {
                "28": 109
            }
        },
        "167": {
            "136": {
                "110": 110
            },
            "38": {
                "171": 235
            }
        },
        "203": {
            "195": {
                "222": 111
            },
            "232": {
                "152": 196
            }
        },
        "168": {
            "233": {
                "159": 112
            }
        },
        "242": {
            "199": {
                "144": 113
            },
            "240": {
                "194": 178
            }
        },
        "222": {
            "108": {
                "246": 114
            },
            "56": {
                "220": 165
            }
        },
        "139": {
            "235": {
                "75": 116
            }
        },
        "192": {
            "121": {
                "178": 117
            },
            "197": {
                "231": 226
            }
        },
        "136": {
            "113": {
                "119": 118
            }
        },
        "187": {
            "170": {
                "238": 119
            }
        },
        "194": {
            "248": {
                "130": 120
            },
            "214": {
                "214": 207
            }
        },
        "235": {
            "191": {
                "242": 121
            },
            "106": {
                "132": 147
            }
        },
        "230": {
            "144": {
                "199": 122
            },
            "252": {
                "234": 195
            }
        },
        "178": {
            "110": {
                "253": 124
            },
            "223": {
                "188": 139
            }
        },
        "141": {
            "186": {
                "233": 125
            }
        },
        "252": {
            "222": {
                "241": 126
            },
            "230": {
                "102": 154
            },
            "134": {
                "83": 210
            }
        },
        "118": {
            "200": {
                "142": 127
            }
        },
        "79": {
            "156": {
                "248": 128
            }
        },
        "241": {
            "180": {
                "174": 129
            },
            "104": {
                "146": 148
            }
        },
        "90": {
            "236": {
                "129": 130
            }
        },
        "114": {
            "200": {
                "218": 131
            }
        },
        "119": {
            "155": {
                "239": 133
            }
        },
        "213": {
            "198": {
                "230": 137
            },
            "117": {
                "229": 145
            }
        },
        "66": {
            "22": {
                "190": 138
            }
        },
        "177": {
            "242": {
                "209": 140
            }
        },
        "217": {
            "206": {
                "117": 141
            },
            "187": {
                "172": 205
            }
        },
        "209": {
            "226": {
                "181": 143
            },
            "228": {
                "194": 223
            }
        },
        "151": {
            "99": {
                "66": 144
            }
        },
        "22": {
            "153": {
                "147": 146
            }
        },
        "109": {
            "241": {
                "164": 149
            }
        },
        "239": {
            "213": {
                "155": 150
            },
            "169": {
                "255": 242
            }
        },
        "155": {
            "164": {
                "98": 153
            },
            "221": {
                "166": 246
            }
        },
        "234": {
            "146": {
                "136": 155
            },
            "132": {
                "248": 182
            }
        },
        "110": {
            "179": {
                "244": 157
            }
        },
        "164": {
            "147": {
                "105": 158
            }
        },
        "204": {
            "243": {
                "247": 159
            }
        },
        "127": {
            "235": {
                "134": 160
            }
        },
        "0": {
            "215": {
                "196": 162
            }
        },
        "161": {
            "163": {
                "180": 164
            }
        },
        "134": {
            "93": {
                "210": 166
            }
        },
        "112": {
            "206": {
                "61": 168
            }
        },
        "245": {
            "175": {
                "148": 169
            },
            "133": {
                "38": 173
            },
            "248": {
                "154": 247
            }
        },
        "183": {
            "53": {
                "202": 170
            }
        },
        "251": {
            "13": {
                "197": 171
            },
            "59": {
                "226": 249
            }
        },
        "228": {
            "193": {
                "244": 172
            },
            "252": {
                "215": 206
            }
        },
        "152": {
            "253": {
                "245": 174
            }
        },
        "129": {
            "177": {
                "197": 175
            }
        },
        "135": {
            "221": {
                "22": 177
            }
        },
        "240": {
            "220": {
                "184": 179
            },
            "202": {
                "151": 217
            }
        },
        "28": {
            "251": {
                "211": 180
            }
        },
        "56": {
            "115": {
                "252": 183
            }
        },
        "125": {
            "154": {
                "155": 184
            }
        },
        "211": {
            "252": {
                "240": 185
            },
            "210": {
                "90": 238
            }
        },
        "202": {
            "69": {
                "158": 186
            },
            "238": {
                "109": 225
            }
        },
        "83": {
            "155": {
                "228": 188
            }
        },
        "185": {
            "233": {
                "246": 189
            }
        },
        "117": {
            "148": {
                "53": 190
            }
        },
        "122": {
            "86": {
                "217": 191
            }
        },
        "69": {
            "244": {
                "212": 194
            }
        },
        "108": {
            "50": {
                "91": 198
            }
        },
        "124": {
            "180": {
                "250": 199
            }
        },
        "195": {
            "229": {
                "85": 201
            }
        },
        "212": {
            "159": {
                "214": 202
            }
        },
        "131": {
            "230": {
                "193": 203
            }
        },
        "157": {
            "118": {
                "42": 204
            }
        },
        "153": {
            "197": {
                "243": 208
            }
        },
        "221": {
            "231": {
                "46": 209
            },
            "220": {
                "190": 218
            }
        },
        "150": {
            "168": {
                "245": 211
            }
        },
        "172": {
            "138": {
                "187": 212
            }
        },
        "193": {
            "46": {
                "113": 215
            }
        },
        "218": {
            "167": {
                "79": 216
            },
            "137": {
                "149": 228
            }
        },
        "106": {
            "184": {
                "175": 219
            }
        },
        "165": {
            "194": {
                "133": 220
            }
        },
        "75": {
            "120": {
                "184": 222
            }
        },
        "38": {
            "75": {
                "223": 224
            }
        },
        "146": {
            "151": {
                "252": 227
            }
        },
        "149": {
            "251": {
                "112": 229
            }
        },
        "34": {
            "204": {
                "71": 230
            }
        },
        "77": {
            "192": {
                "180": 231
            }
        },
        "61": {
            "182": {
                "81": 234
            }
        },
        "126": {
            "189": {
                "122": 236
            }
        },
        "88": {
            "225": {
                "96": 237
            }
        },
        "154": {
            "208": {
                "56": 239
            }
        },
        "188": {
            "210": {
                "253": 248
            }
        },
        "207": {
            "91": {
                "108": 250
            }
        },
        "128": {
            "129": {
                "189": 252
            }
        },
        "59": {
            "234": {
                "200": 253
            }
        },
        "181": {
            "231": {
                "209": 254
            }
        }
    }
}